reader/__init__.py
reader/__main__.py
reader/config.toml
reader/feed.py
reader/viewer.py
nto218145-1.1.25.dist-info/METADATA
nto218145-1.1.25.dist-info/WHEEL
nto218145-1.1.25.dist-info/entry_points.txt
nto218145-1.1.25.dist-info/top_level.txt
nto218145-1.1.25.dist-info/RECORD
